tests/__init__.py
tests/test_cli.py
tests/test_templateengine.py
tests/test_website.py
tests/test_webstaterator.py
webstaterator/__init__.py
webstaterator/__main__.py
webstaterator/cli.py
webstaterator/templateengine.py
webstaterator/website.py
webstaterator/webstaterator.py
webstaterator-0.4.2.dist-info/LICENSE
webstaterator-0.4.2.dist-info/METADATA
webstaterator-0.4.2.dist-info/WHEEL
webstaterator-0.4.2.dist-info/entry_points.txt
webstaterator-0.4.2.dist-info/top_level.txt
webstaterator-0.4.2.dist-info/RECORD
