Metadata-Version: 2.1
Name: webstaterator
Version: 0.4.2
Summary: A Python tool for generating static websites based on JOSN models
Home-page: https://gitlab.com/Jon.Keatley.Folio/webstaterator
Author: Jon Keatley
Project-URL: Source Code, https://gitlab.com/Jon.Keatley.Folio/webstaterator
Keywords: website static webpages generator json
Classifier: Development Status :: 3 - Alpha
Classifier: Programming Language :: Python :: 3
Classifier: License :: OSI Approved :: MIT License
Classifier: Operating System :: OS Independent
Requires-Python: >=3.6
License-File: LICENSE
Requires-Dist: jinja2 (==2.11.2)
Requires-Dist: markupsafe (==1.1.0)
Requires-Dist: markdown (==3.3.7)
